webvpn/__init__.py
webvpn/client.py
webvpn/cmd.py
webvpn/config.py
webvpn/gateway/__init__.py
webvpn/gateway/gateway.py
webvpn/gateway/tcp.py
webvpn/gateway/webvpn.py
webvpn/logger.py
webvpn/login.py
webvpn/server.py
webvpn/settings.yaml
webvpn-0.1.6.dist-info/WHEEL
webvpn-0.1.6.dist-info/entry_points.txt
webvpn-0.1.6.dist-info/METADATA
webvpn-0.1.6.dist-info/RECORD
