Metadata-Version: 2.1
Name: webvpn
Version: 0.1.6
Summary: TCP over WebVPN
License: MIT
Author: Ming Yang
Author-email: ymviv@qq.com
Requires-Python: >=3.8,<4.0
Classifier: License :: OSI Approved :: MIT License
Classifier: Programming Language :: Python :: 3
Classifier: Programming Language :: Python :: 3.8
Classifier: Programming Language :: Python :: 3.9
Classifier: Programming Language :: Python :: 3.10
Classifier: Programming Language :: Python :: 3.11
Requires-Dist: aiohttp (>=3.8.1,<4.0.0)
Requires-Dist: aiorun (>=2022.4.1,<2023.0.0)
Requires-Dist: beautifulsoup4 (>=4.11.1,<5.0.0)
Requires-Dist: dynaconf (>=3.1.8,<4.0.0)
Requires-Dist: sentry-sdk (>=1.5.12,<2.0.0)
Requires-Dist: shellingham (>=1.4.0,<2.0.0)
Requires-Dist: typer (>=0.4.1,<0.5.0)
